signal_handler/__init__.py
signal_handler/handlers.py
django_signal_handler-0.1.1.dist-info/LICENSE
django_signal_handler-0.1.1.dist-info/METADATA
django_signal_handler-0.1.1.dist-info/WHEEL
django_signal_handler-0.1.1.dist-info/top_level.txt
django_signal_handler-0.1.1.dist-info/RECORD
