Metadata-Version: 2.1
Name: django-signal-handler
Version: 0.1.1
Summary: A package for handling Django model signals.
Home-page: https://github.com/konradbeck/django-signal-handler.git
Author: Konrad Beck
Author-email: konradbeck101@gmail.com
Classifier: Programming Language :: Python :: 3
Classifier: License :: OSI Approved :: MIT License
Classifier: Operating System :: OS Independent
Classifier: Framework :: Django
Classifier: Framework :: Django :: 3.2
Classifier: Framework :: Django :: 4.0
Requires-Python: >=3.6
License-File: LICENSE
Requires-Dist: django>=3.0
Provides-Extra: dev
Requires-Dist: pytest; extra == "dev"
Requires-Dist: pytest-django; extra == "dev"
